LICENSE
README.md
setup.py
ai2e.egg-info/PKG-INFO
ai2e.egg-info/SOURCES.txt
ai2e.egg-info/dependency_links.txt
ai2e.egg-info/not-zip-safe
ai2e.egg-info/requires.txt
ai2e.egg-info/top_level.txt
connectai/__init__.py
connectai/broker.py
connectai/ctx.py
connectai/event.py
connectai/globals.py
connectai/message.py
connectai/bot/__init__.py
connectai/bot/base.py
connectai/bot/feishu.py