Metadata-Version: 2.1
Name: ai2e
Version: 0.0.4
Summary: lark(feishu) client
Home-page: UNKNOWN
Author: lloydzhou@gmail.com
License: MIT
Project-URL: Documentation, https://www.connectai-e.com
Project-URL: Code, http://github.com/connectAI-E/connectai
Project-URL: Issue tracker, http://github.com/connectAI-E/connectai/issues
Keywords: Feishu,Lark,Webhook,Websocket,Bot
Platform: UNKNOWN
License-File: LICENSE
